{
  "trips": [
    {
      "Purpose Of Visit": "Personal Travel",
      "TR No": "DT00000595",
      "Multicity Id": "642",
      "Service Id": "207",
      "Trip End Date": "2017-05-16",
      "Project Name": "",
      "trip_req_id": "255",
      "Traveller Id": "318",
      "Origin City": "Bangalore, Karnataka, India",
      "Destination City": "Pune, Maharashtra, India",
      "Trip Start Date": "2017-05-16"
    },
    {
      "Purpose Of Visit": "Personal Travel",
      "TR No": "DT00000594",
      "Multicity Id": "640",
      "Service Id": "206",
      "Trip End Date": "2017-05-23",
      "Project Name": "",
      "trip_req_id": "254",
      "Traveller Id": "317",
      "Origin City": "Bangalore, Karnataka, India",
      "Destination City": "Pune, Maharashtra, India",
      "Trip Start Date": "2017-05-23"
    },
    {
      "Purpose Of Visit": "Personal Travel",
      "TR No": "DT00000593",
      "Multicity Id": "638",
      "Service Id": "205",
      "Trip End Date": "2017-05-23",
      "Project Name": "",
      "trip_req_id": "253",
      "Traveller Id": "316",
      "Origin City": "Bangalore, Karnataka, India",
      "Destination City": "Pune, Maharashtra, India",
      "Trip Start Date": "2017-05-23"
    },
    {
      "Purpose Of Visit": "Personal Travel",
      "TR No": "DT00000592",
      "Multicity Id": "636",
      "Service Id": "204",
      "Trip End Date": "2017-05-22",
      "Project Name": "",
      "trip_req_id": "252",
      "Traveller Id": "315",
      "Origin City": "Bangalore, Karnataka, India",
      "Destination City": "Pune, Maharashtra, India",
      "Trip Start Date": "2017-05-22"
    },
    {
      "Purpose Of Visit": "Personal Travel",
      "TR No": "DT00000591",
      "Multicity Id": "634",
      "Service Id": "203",
      "Trip End Date": "2017-05-22",
      "Project Name": "",
      "trip_req_id": "251",
      "Traveller Id": "314",
      "Origin City": "Bangalore, Karnataka, India",
      "Destination City": "Pune, Maharashtra, India",
      "Trip Start Date": "2017-05-22"
    },
    {
      "Purpose Of Visit": "Personal Travel",
      "TR No": "DT00000590",
      "Multicity Id": "632",
      "Service Id": "202",
      "Trip End Date": "2017-05-22",
      "Project Name": "",
      "trip_req_id": "250",
      "Traveller Id": "313",
      "Origin City": "Bangalore, Karnataka, India",
      "Destination City": "Pune, Maharashtra, India",
      "Trip Start Date": "2017-05-22"
    },
    {
      "Purpose Of Visit": "Personal Travel",
      "TR No": "DT00000589",
      "Multicity Id": "630",
      "Service Id": "201",
      "Trip End Date": "2017-05-22",
      "Project Name": "",
      "trip_req_id": "249",
      "Traveller Id": "312",
      "Origin City": "Bangalore, Karnataka, India",
      "Destination City": "Pune, Maharashtra, India",
      "Trip Start Date": "2017-05-22"
    },
    {
      "Purpose Of Visit": "Personal Travel",
      "TR No": "DT00000588",
      "Multicity Id": "628",
      "Service Id": "200",
      "Trip End Date": "2017-05-19",
      "Project Name": "",
      "trip_req_id": "248",
      "Traveller Id": "311",
      "Origin City": "Bangalore, Karnataka, India",
      "Destination City": "Pune, Maharashtra, India",
      "Trip Start Date": "2017-05-19"
    },
    {
      "Purpose Of Visit": "Personal Travel",
      "TR No": "DT00000587",
      "Multicity Id": "626",
      "Service Id": "199",
      "Trip End Date": "2017-05-19",
      "Project Name": "",
      "trip_req_id": "247",
      "Traveller Id": "310",
      "Origin City": "Bangalore, Karnataka, India",
      "Destination City": "Pune, Maharashtra, India",
      "Trip Start Date": "2017-05-19"
    },
    {
      "Purpose Of Visit": "Personal Travel",
      "TR No": "DT00000586",
      "Multicity Id": "624",
      "Service Id": "198",
      "Trip End Date": "2017-05-26",
      "Project Name": "",
      "trip_req_id": "246",
      "Traveller Id": "309",
      "Origin City": "Bangalore, Karnataka, India",
      "Destination City": "Pune, Maharashtra, India",
      "Trip Start Date": "2017-05-26"
    }
  ],
  "status": "Success"
}